{
    "actors": [
        {
            "components": [
                {
                    "data": {
                        "mass": 0.0,
                        "physics_simulation": true,
                        "transform": {
                            "pos": [
                                5.0,
                                -0.5,
                                0.0
                            ],
                            "rot": [
                                0.0,
                                0.0,
                                0.0,
                                1.0
                            ],
                            "scale": [
                                20.0,
                                0.5,
                                20.0
                            ]
                        },
                        "type": 0
                    },
                    "id": "fbd371fb-73ff-4fa7-b784-450e264fe022",
                    "name": "RigidBodyCubeComponent"
                },
                {
                    "data": {
                        "mesh_path": "../Assets/box.fbx/Cube",
                        "transform": {
                            "pos": [
                                0.0,
                                0.0,
                                0.0
                            ],
                            "rot": [
                                0.0,
                                0.0,
                                0.0,
                                1.0
                            ],
                            "scale": [
                                1.0,
                                1.0,
                                1.0
                            ]
                        }
                    },
                    "id": "fe1074a8-beb0-4854-976f-7f5f96120a6d",
                    "name": "StaticMeshRenderer",
                    "parent": "fbd371fb-73ff-4fa7-b784-450e264fe022"
                },
                {
                    "data": {
                        "channel_id": -1,
                        "name": "",
                        "transform": {
                            "pos": [
                                0.0,
                                0.0,
                                0.0
                            ],
                            "rot": [
                                0.0,
                                0.0,
                                0.0,
                                1.0
                            ],
                            "scale": [
                                1.0,
                                1.0,
                                1.0
                            ]
                        }
                    },
                    "id": "2fd1db81-4df5-40a7-be2e-873598e49b8c",
                    "name": "SceneComponent",
                    "parent": "fbd371fb-73ff-4fa7-b784-450e264fe022"
                }
            ],
            "id": "9780bb48-6690-4ed4-bb5e-2963af402924"
        },
        {
            "components": [
                {
                    "data": {
                        "mass": 1.0,
                        "physics_simulation": true,
                        "transform": {
                            "pos": [
                                0.0,
                                40.0,
                                0.0
                            ],
                            "rot": [
                                0.3535533845424652,
                                0.3535533845424652,
                                -0.1464466005563736,
                                0.8535533547401428
                            ],
                            "scale": [
                                1.0,
                                1.0,
                                1.0
                            ]
                        },
                        "type": 1
                    },
                    "id": "3d6a6816-6875-4413-934f-9ae6a2cf83d8",
                    "name": "RigidBodyCubeComponent"
                },
                {
                    "data": {
                        "mass": 1.0,
                        "physics_simulation": true,
                        "transform": {
                            "pos": [
                                0.0,
                                0.0,
                                0.0
                            ],
                            "rot": [
                                0.0,
                                0.0,
                                0.0,
                                1.0
                            ],
                            "scale": [
                                1.0,
                                1.0,
                                1.0
                            ]
                        },
                        "type": 1
                    },
                    "id": "4a8b75aa-68e8-4b02-a38f-b468be8848fa",
                    "name": "RigidBodyCubeComponent",
                    "parent": "3d6a6816-6875-4413-934f-9ae6a2cf83d8"
                },
                {
                    "data": {
                        "mesh_path": "../Assets/box.fbx/Cube",
                        "transform": {
                            "pos": [
                                0.0,
                                0.0,
                                0.0
                            ],
                            "rot": [
                                0.0,
                                0.0,
                                0.0,
                                1.0
                            ],
                            "scale": [
                                1.0,
                                1.0,
                                1.0
                            ]
                        }
                    },
                    "id": "557ca054-645e-4818-8eac-df87ee8e03f4",
                    "name": "StaticMeshRenderer",
                    "parent": "3d6a6816-6875-4413-934f-9ae6a2cf83d8"
                }
            ],
            "id": "9affb1b9-9188-4c44-bb45-d508e97b7ce0"
        },
        {
            "components": [
                {
                    "data": {
                        "mass": 1.0,
                        "physics_simulation": true,
                        "transform": {
                            "pos": [
                                0.0,
                                41.0,
                                0.0
                            ],
                            "rot": [
                                0.3535533845424652,
                                0.3535533845424652,
                                -0.1464466005563736,
                                0.8535533547401428
                            ],
                            "scale": [
                                1.0,
                                1.0,
                                1.0
                            ]
                        },
                        "type": 1
                    },
                    "id": "56fd1a86-9880-4be3-85c3-25a1b0218ac9",
                    "name": "RigidBodyCubeComponent"
                },
                {
                    "data": {
                        "mass": 1.0,
                        "physics_simulation": true,
                        "transform": {
                            "pos": [
                                0.0,
                                0.0,
                                0.0
                            ],
                            "rot": [
                                0.0,
                                0.0,
                                0.0,
                                1.0
                            ],
                            "scale": [
                                1.0,
                                1.0,
                                1.0
                            ]
                        },
                        "type": 1
                    },
                    "id": "1776b286-9faf-47f4-bd71-065a1f699501",
                    "name": "RigidBodyCubeComponent",
                    "parent": "56fd1a86-9880-4be3-85c3-25a1b0218ac9"
                },
                {
                    "data": {
                        "mesh_path": "../Assets/box.fbx/Cube",
                        "transform": {
                            "pos": [
                                0.0,
                                0.0,
                                0.0
                            ],
                            "rot": [
                                0.0,
                                0.0,
                                0.0,
                                1.0
                            ],
                            "scale": [
                                1.0,
                                1.0,
                                1.0
                            ]
                        }
                    },
                    "id": "2484e220-c6db-48eb-95ad-4e88a053f364",
                    "name": "StaticMeshRenderer",
                    "parent": "56fd1a86-9880-4be3-85c3-25a1b0218ac9"
                }
            ],
            "id": "9b758b6a-75ae-4372-8583-d9ae82e0de78"
        },
        {
            "components": [
                {
                    "data": {
                        "mass": 1.0,
                        "physics_simulation": true,
                        "transform": {
                            "pos": [
                                0.0,
                                42.0,
                                0.0
                            ],
                            "rot": [
                                0.3535533845424652,
                                0.3535533845424652,
                                -0.1464466005563736,
                                0.8535533547401428
                            ],
                            "scale": [
                                1.0,
                                1.0,
                                1.0
                            ]
                        },
                        "type": 1
                    },
                    "id": "c4b4ab68-b925-4ea3-9045-b38aa1f0fd6a",
                    "name": "RigidBodyCubeComponent"
                },
                {
                    "data": {
                        "mass": 1.0,
                        "physics_simulation": true,
                        "transform": {
                            "pos": [
                                0.0,
                                0.0,
                                0.0
                            ],
                            "rot": [
                                0.0,
                                0.0,
                                0.0,
                                1.0
                            ],
                            "scale": [
                                1.0,
                                1.0,
                                1.0
                            ]
                        },
                        "type": 1
                    },
                    "id": "46d081ba-8262-4097-b47e-b2012754e788",
                    "name": "RigidBodyCubeComponent",
                    "parent": "c4b4ab68-b925-4ea3-9045-b38aa1f0fd6a"
                },
                {
                    "data": {
                        "mesh_path": "../Assets/box.fbx/Cube",
                        "transform": {
                            "pos": [
                                0.0,
                                0.0,
                                0.0
                            ],
                            "rot": [
                                0.0,
                                0.0,
                                0.0,
                                1.0
                            ],
                            "scale": [
                                1.0,
                                1.0,
                                1.0
                            ]
                        }
                    },
                    "id": "73a9fac4-6d89-42c3-a6c5-46f1fcf6b6bd",
                    "name": "StaticMeshRenderer",
                    "parent": "c4b4ab68-b925-4ea3-9045-b38aa1f0fd6a"
                }
            ],
            "id": "178aeaac-2857-4374-8079-cc7d84a4d35d"
        },
        {
            "components": [
                {
                    "data": {
                        "mass": 1.0,
                        "physics_simulation": true,
                        "transform": {
                            "pos": [
                                0.0,
                                43.0,
                                0.0
                            ],
                            "rot": [
                                0.3535533845424652,
                                0.3535533845424652,
                                -0.1464466005563736,
                                0.8535533547401428
                            ],
                            "scale": [
                                1.0,
                                1.0,
                                1.0
                            ]
                        },
                        "type": 1
                    },
                    "id": "4dee3480-0560-4353-9c42-307890aa657b",
                    "name": "RigidBodyCubeComponent"
                },
                {
                    "data": {
                        "mass": 1.0,
                        "physics_simulation": true,
                        "transform": {
                            "pos": [
                                0.0,
                                0.0,
                                0.0
                            ],
                            "rot": [
                                0.0,
                                0.0,
                                0.0,
                                1.0
                            ],
                            "scale": [
                                1.0,
                                1.0,
                                1.0
                            ]
                        },
                        "type": 1
                    },
                    "id": "20f73614-dd4b-45f1-82dd-248ce292bdb9",
                    "name": "RigidBodyCubeComponent",
                    "parent": "4dee3480-0560-4353-9c42-307890aa657b"
                },
                {
                    "data": {
                        "mesh_path": "../Assets/box.fbx/Cube",
                        "transform": {
                            "pos": [
                                0.0,
                                0.0,
                                0.0
                            ],
                            "rot": [
                                0.0,
                                0.0,
                                0.0,
                                1.0
                            ],
                            "scale": [
                                1.0,
                                1.0,
                                1.0
                            ]
                        }
                    },
                    "id": "d8d205a9-b701-48ce-8cd3-2ca664ed5f97",
                    "name": "StaticMeshRenderer",
                    "parent": "4dee3480-0560-4353-9c42-307890aa657b"
                }
            ],
            "id": "30dc242e-51f9-4237-90a5-d3b16c4ffac8"
        },
        {
            "components": [
                {
                    "data": {
                        "mass": 1.0,
                        "physics_simulation": true,
                        "transform": {
                            "pos": [
                                0.0,
                                44.0,
                                0.0
                            ],
                            "rot": [
                                0.3535533845424652,
                                0.3535533845424652,
                                -0.1464466005563736,
                                0.8535533547401428
                            ],
                            "scale": [
                                1.0,
                                1.0,
                                1.0
                            ]
                        },
                        "type": 1
                    },
                    "id": "25b73e9d-a612-4681-8536-53240887e607",
                    "name": "RigidBodyCubeComponent"
                },
                {
                    "data": {
                        "mass": 1.0,
                        "physics_simulation": true,
                        "transform": {
                            "pos": [
                                0.0,
                                0.0,
                                0.0
                            ],
                            "rot": [
                                0.0,
                                0.0,
                                0.0,
                                1.0
                            ],
                            "scale": [
                                1.0,
                                1.0,
                                1.0
                            ]
                        },
                        "type": 1
                    },
                    "id": "9e3c6277-600e-4422-aaad-2cf23100a837",
                    "name": "RigidBodyCubeComponent",
                    "parent": "25b73e9d-a612-4681-8536-53240887e607"
                },
                {
                    "data": {
                        "mesh_path": "../Assets/box.fbx/Cube",
                        "transform": {
                            "pos": [
                                0.0,
                                0.0,
                                0.0
                            ],
                            "rot": [
                                0.0,
                                0.0,
                                0.0,
                                1.0
                            ],
                            "scale": [
                                1.0,
                                1.0,
                                1.0
                            ]
                        }
                    },
                    "id": "317725bf-3817-4051-ac35-42601c7ce15e",
                    "name": "StaticMeshRenderer",
                    "parent": "25b73e9d-a612-4681-8536-53240887e607"
                }
            ],
            "id": "be401359-3c16-4466-8f3f-8618414b1242"
        },
        {
            "components": [
                {
                    "data": {
                        "mass": 1.0,
                        "physics_simulation": true,
                        "transform": {
                            "pos": [
                                1.0,
                                40.0,
                                0.0
                            ],
                            "rot": [
                                0.3535533845424652,
                                0.3535533845424652,
                                -0.1464466005563736,
                                0.8535533547401428
                            ],
                            "scale": [
                                1.0,
                                1.0,
                                1.0
                            ]
                        },
                        "type": 1
                    },
                    "id": "547b663f-d63b-4f2e-a47a-dd7b4ba16ef7",
                    "name": "RigidBodyCubeComponent"
                },
                {
                    "data": {
                        "mass": 1.0,
                        "physics_simulation": true,
                        "transform": {
                            "pos": [
                                0.0,
                                0.0,
                                0.0
                            ],
                            "rot": [
                                0.0,
                                0.0,
                                0.0,
                                1.0
                            ],
                            "scale": [
                                1.0,
                                1.0,
                                1.0
                            ]
                        },
                        "type": 1
                    },
                    "id": "4a39ed17-4b1c-4eb6-bd6b-d6d96d80655c",
                    "name": "RigidBodyCubeComponent",
                    "parent": "547b663f-d63b-4f2e-a47a-dd7b4ba16ef7"
                },
                {
                    "data": {
                        "mesh_path": "../Assets/box.fbx/Cube",
                        "transform": {
                            "pos": [
                                0.0,
                                0.0,
                                0.0
                            ],
                            "rot": [
                                0.0,
                                0.0,
                                0.0,
                                1.0
                            ],
                            "scale": [
                                1.0,
                                1.0,
                                1.0
                            ]
                        }
                    },
                    "id": "45d952a8-0bbb-474b-93c7-d1e9ed8b8c80",
                    "name": "StaticMeshRenderer",
                    "parent": "547b663f-d63b-4f2e-a47a-dd7b4ba16ef7"
                }
            ],
            "id": "470a5427-0208-4f1c-93e3-dd4b33585f47"
        },
        {
            "components": [
                {
                    "data": {
                        "mass": 1.0,
                        "physics_simulation": true,
                        "transform": {
                            "pos": [
                                1.0,
                                41.0,
                                0.0
                            ],
                            "rot": [
                                0.3535533845424652,
                                0.3535533845424652,
                                -0.1464466005563736,
                                0.8535533547401428
                            ],
                            "scale": [
                                1.0,
                                1.0,
                                1.0
                            ]
                        },
                        "type": 1
                    },
                    "id": "6cbb4783-68ed-49ef-9ba1-72005af54c12",
                    "name": "RigidBodyCubeComponent"
                },
                {
                    "data": {
                        "mass": 1.0,
                        "physics_simulation": true,
                        "transform": {
                            "pos": [
                                0.0,
                                0.0,
                                0.0
                            ],
                            "rot": [
                                0.0,
                                0.0,
                                0.0,
                                1.0
                            ],
                            "scale": [
                                1.0,
                                1.0,
                                1.0
                            ]
                        },
                        "type": 1
                    },
                    "id": "e997c7ba-15e5-4990-910b-e1d590a1e043",
                    "name": "RigidBodyCubeComponent",
                    "parent": "6cbb4783-68ed-49ef-9ba1-72005af54c12"
                },
                {
                    "data": {
                        "mesh_path": "../Assets/box.fbx/Cube",
                        "transform": {
                            "pos": [
                                0.0,
                                0.0,
                                0.0
                            ],
                            "rot": [
                                0.0,
                                0.0,
                                0.0,
                                1.0
                            ],
                            "scale": [
                                1.0,
                                1.0,
                                1.0
                            ]
                        }
                    },
                    "id": "47df4037-ad71-4ad0-96cc-299728997c01",
                    "name": "StaticMeshRenderer",
                    "parent": "6cbb4783-68ed-49ef-9ba1-72005af54c12"
                }
            ],
            "id": "879aca39-878e-4ab2-80a6-16aefc77d6af"
        },
        {
            "components": [
                {
                    "data": {
                        "mass": 1.0,
                        "physics_simulation": true,
                        "transform": {
                            "pos": [
                                1.0,
                                42.0,
                                0.0
                            ],
                            "rot": [
                                0.3535533845424652,
                                0.3535533845424652,
                                -0.1464466005563736,
                                0.8535533547401428
                            ],
                            "scale": [
                                1.0,
                                1.0,
                                1.0
                            ]
                        },
                        "type": 1
                    },
                    "id": "9a584b93-e26d-4ea8-a9a5-a38f20ea692c",
                    "name": "RigidBodyCubeComponent"
                },
                {
                    "data": {
                        "mass": 1.0,
                        "physics_simulation": true,
                        "transform": {
                            "pos": [
                                0.0,
                                0.0,
                                0.0
                            ],
                            "rot": [
                                0.0,
                                0.0,
                                0.0,
                                1.0
                            ],
                            "scale": [
                                1.0,
                                1.0,
                                1.0
                            ]
                        },
                        "type": 1
                    },
                    "id": "d5fbe063-0303-47ee-a385-1210fb5ec0a6",
                    "name": "RigidBodyCubeComponent",
                    "parent": "9a584b93-e26d-4ea8-a9a5-a38f20ea692c"
                },
                {
                    "data": {
                        "mesh_path": "../Assets/box.fbx/Cube",
                        "transform": {
                            "pos": [
                                0.0,
                                0.0,
                                0.0
                            ],
                            "rot": [
                                0.0,
                                0.0,
                                0.0,
                                1.0
                            ],
                            "scale": [
                                1.0,
                                1.0,
                                1.0
                            ]
                        }
                    },
                    "id": "5f891bcf-db5f-4e97-9caf-ccc035b34e85",
                    "name": "StaticMeshRenderer",
                    "parent": "9a584b93-e26d-4ea8-a9a5-a38f20ea692c"
                }
            ],
            "id": "b37875e5-9075-449f-87a5-778d80758cf9"
        },
        {
            "components": [
                {
                    "data": {
                        "mass": 1.0,
                        "physics_simulation": true,
                        "transform": {
                            "pos": [
                                1.0,
                                43.0,
                                0.0
                            ],
                            "rot": [
                                0.3535533845424652,
                                0.3535533845424652,
                                -0.1464466005563736,
                                0.8535533547401428
                            ],
                            "scale": [
                                1.0,
                                1.0,
                                1.0
                            ]
                        },
                        "type": 1
                    },
                    "id": "7fcdd8af-0b34-424b-97ae-03e03b4b8cc3",
                    "name": "RigidBodyCubeComponent"
                },
                {
                    "data": {
                        "mass": 1.0,
                        "physics_simulation": true,
                        "transform": {
                            "pos": [
                                0.0,
                                0.0,
                                0.0
                            ],
                            "rot": [
                                0.0,
                                0.0,
                                0.0,
                                1.0
                            ],
                            "scale": [
                                1.0,
                                1.0,
                                1.0
                            ]
                        },
                        "type": 1
                    },
                    "id": "4b5db367-183d-4387-87c7-1201ddc6bad6",
                    "name": "RigidBodyCubeComponent",
                    "parent": "7fcdd8af-0b34-424b-97ae-03e03b4b8cc3"
                },
                {
                    "data": {
                        "mesh_path": "../Assets/box.fbx/Cube",
                        "transform": {
                            "pos": [
                                0.0,
                                0.0,
                                0.0
                            ],
                            "rot": [
                                0.0,
                                0.0,
                                0.0,
                                1.0
                            ],
                            "scale": [
                                1.0,
                                1.0,
                                1.0
                            ]
                        }
                    },
                    "id": "79f116b1-a730-422b-b7a7-69774a544ce9",
                    "name": "StaticMeshRenderer",
                    "parent": "7fcdd8af-0b34-424b-97ae-03e03b4b8cc3"
                }
            ],
            "id": "e6239121-6e4c-433d-a88d-b5a24990b2e7"
        },
        {
            "components": [
                {
                    "data": {
                        "mass": 1.0,
                        "physics_simulation": true,
                        "transform": {
                            "pos": [
                                1.0,
                                44.0,
                                0.0
                            ],
                            "rot": [
                                0.3535533845424652,
                                0.3535533845424652,
                                -0.1464466005563736,
                                0.8535533547401428
                            ],
                            "scale": [
                                1.0,
                                1.0,
                                1.0
                            ]
                        },
                        "type": 1
                    },
                    "id": "ccc8d3cd-8f95-4f90-ac63-c793afee8c86",
                    "name": "RigidBodyCubeComponent"
                },
                {
                    "data": {
                        "mass": 1.0,
                        "physics_simulation": true,
                        "transform": {
                            "pos": [
                                0.0,
                                0.0,
                                0.0
                            ],
                            "rot": [
                                0.0,
                                0.0,
                                0.0,
                                1.0
                            ],
                            "scale": [
                                1.0,
                                1.0,
                                1.0
                            ]
                        },
                        "type": 1
                    },
                    "id": "95cb69ce-a547-44ee-8ac4-38ff8a955d5c",
                    "name": "RigidBodyCubeComponent",
                    "parent": "ccc8d3cd-8f95-4f90-ac63-c793afee8c86"
                },
                {
                    "data": {
                        "mesh_path": "../Assets/box.fbx/Cube",
                        "transform": {
                            "pos": [
                                0.0,
                                0.0,
                                0.0
                            ],
                            "rot": [
                                0.0,
                                0.0,
                                0.0,
                                1.0
                            ],
                            "scale": [
                                1.0,
                                1.0,
                                1.0
                            ]
                        }
                    },
                    "id": "c5404d87-79cf-44fb-8216-d7d138095877",
                    "name": "StaticMeshRenderer",
                    "parent": "ccc8d3cd-8f95-4f90-ac63-c793afee8c86"
                }
            ],
            "id": "75ee4470-337e-4696-9946-4d134ec740b0"
        },
        {
            "components": [
                {
                    "data": {
                        "mass": 1.0,
                        "physics_simulation": true,
                        "transform": {
                            "pos": [
                                2.0,
                                40.0,
                                0.0
                            ],
                            "rot": [
                                0.3535533845424652,
                                0.3535533845424652,
                                -0.1464466005563736,
                                0.8535533547401428
                            ],
                            "scale": [
                                1.0,
                                1.0,
                                1.0
                            ]
                        },
                        "type": 1
                    },
                    "id": "afd57f93-28dc-4ef8-adca-31e02282cc29",
                    "name": "RigidBodyCubeComponent"
                },
                {
                    "data": {
                        "mass": 1.0,
                        "physics_simulation": true,
                        "transform": {
                            "pos": [
                                0.0,
                                0.0,
                                0.0
                            ],
                            "rot": [
                                0.0,
                                0.0,
                                0.0,
                                1.0
                            ],
                            "scale": [
                                1.0,
                                1.0,
                                1.0
                            ]
                        },
                        "type": 1
                    },
                    "id": "f8e87b68-1815-41ed-abb3-05e6b158bc63",
                    "name": "RigidBodyCubeComponent",
                    "parent": "afd57f93-28dc-4ef8-adca-31e02282cc29"
                },
                {
                    "data": {
                        "mesh_path": "../Assets/box.fbx/Cube",
                        "transform": {
                            "pos": [
                                0.0,
                                0.0,
                                0.0
                            ],
                            "rot": [
                                0.0,
                                0.0,
                                0.0,
                                1.0
                            ],
                            "scale": [
                                1.0,
                                1.0,
                                1.0
                            ]
                        }
                    },
                    "id": "0b5d91c9-7215-4fc6-847a-c3cac7028394",
                    "name": "StaticMeshRenderer",
                    "parent": "afd57f93-28dc-4ef8-adca-31e02282cc29"
                }
            ],
            "id": "8d73333b-c719-4f5d-8a49-29269f132d51"
        },
        {
            "components": [
                {
                    "data": {
                        "mass": 1.0,
                        "physics_simulation": true,
                        "transform": {
                            "pos": [
                                2.0,
                                41.0,
                                0.0
                            ],
                            "rot": [
                                0.3535533845424652,
                                0.3535533845424652,
                                -0.1464466005563736,
                                0.8535533547401428
                            ],
                            "scale": [
                                1.0,
                                1.0,
                                1.0
                            ]
                        },
                        "type": 1
                    },
                    "id": "f054e101-21a9-481d-aa2e-37863a0f0e83",
                    "name": "RigidBodyCubeComponent"
                },
                {
                    "data": {
                        "mass": 1.0,
                        "physics_simulation": true,
                        "transform": {
                            "pos": [
                                0.0,
                                0.0,
                                0.0
                            ],
                            "rot": [
                                0.0,
                                0.0,
                                0.0,
                                1.0
                            ],
                            "scale": [
                                1.0,
                                1.0,
                                1.0
                            ]
                        },
                        "type": 1
                    },
                    "id": "6a4335dd-cce8-4421-b248-9514930f30cb",
                    "name": "RigidBodyCubeComponent",
                    "parent": "f054e101-21a9-481d-aa2e-37863a0f0e83"
                },
                {
                    "data": {
                        "mesh_path": "../Assets/box.fbx/Cube",
                        "transform": {
                            "pos": [
                                0.0,
                                0.0,
                                0.0
                            ],
                            "rot": [
                                0.0,
                                0.0,
                                0.0,
                                1.0
                            ],
                            "scale": [
                                1.0,
                                1.0,
                                1.0
                            ]
                        }
                    },
                    "id": "a67a5498-2deb-43ce-9d0d-c8e8df166297",
                    "name": "StaticMeshRenderer",
                    "parent": "f054e101-21a9-481d-aa2e-37863a0f0e83"
                }
            ],
            "id": "b7957bec-03d5-475b-9afb-a279e5798fcf"
        },
        {
            "components": [
                {
                    "data": {
                        "mass": 1.0,
                        "physics_simulation": true,
                        "transform": {
                            "pos": [
                                2.0,
                                42.0,
                                0.0
                            ],
                            "rot": [
                                0.3535533845424652,
                                0.3535533845424652,
                                -0.1464466005563736,
                                0.8535533547401428
                            ],
                            "scale": [
                                1.0,
                                1.0,
                                1.0
                            ]
                        },
                        "type": 1
                    },
                    "id": "5e7927e6-6a20-4ec1-8800-bccd1beda970",
                    "name": "RigidBodyCubeComponent"
                },
                {
                    "data": {
                        "mass": 1.0,
                        "physics_simulation": true,
                        "transform": {
                            "pos": [
                                0.0,
                                0.0,
                                0.0
                            ],
                            "rot": [
                                0.0,
                                0.0,
                                0.0,
                                1.0
                            ],
                            "scale": [
                                1.0,
                                1.0,
                                1.0
                            ]
                        },
                        "type": 1
                    },
                    "id": "1419f6e9-3678-4c37-bb31-15d1b50f0b04",
                    "name": "RigidBodyCubeComponent",
                    "parent": "5e7927e6-6a20-4ec1-8800-bccd1beda970"
                },
                {
                    "data": {
                        "mesh_path": "../Assets/box.fbx/Cube",
                        "transform": {
                            "pos": [
                                0.0,
                                0.0,
                                0.0
                            ],
                            "rot": [
                                0.0,
                                0.0,
                                0.0,
                                1.0
                            ],
                            "scale": [
                                1.0,
                                1.0,
                                1.0
                            ]
                        }
                    },
                    "id": "04fbd3d6-6539-41f2-9d02-1a44771eeb2a",
                    "name": "StaticMeshRenderer",
                    "parent": "5e7927e6-6a20-4ec1-8800-bccd1beda970"
                }
            ],
            "id": "f27dc76d-c277-47bd-9262-7287528e0d9b"
        },
        {
            "components": [
                {
                    "data": {
                        "mass": 1.0,
                        "physics_simulation": true,
                        "transform": {
                            "pos": [
                                2.0,
                                43.0,
                                0.0
                            ],
                            "rot": [
                                0.3535533845424652,
                                0.3535533845424652,
                                -0.1464466005563736,
                                0.8535533547401428
                            ],
                            "scale": [
                                1.0,
                                1.0,
                                1.0
                            ]
                        },
                        "type": 1
                    },
                    "id": "2fcbd43a-f12e-48e6-a392-d4e60377cbc2",
                    "name": "RigidBodyCubeComponent"
                },
                {
                    "data": {
                        "mass": 1.0,
                        "physics_simulation": true,
                        "transform": {
                            "pos": [
                                0.0,
                                0.0,
                                0.0
                            ],
                            "rot": [
                                0.0,
                                0.0,
                                0.0,
                                1.0
                            ],
                            "scale": [
                                1.0,
                                1.0,
                                1.0
                            ]
                        },
                        "type": 1
                    },
                    "id": "271795ad-e4ff-4e55-b5c8-2c01d2c91dc0",
                    "name": "RigidBodyCubeComponent",
                    "parent": "2fcbd43a-f12e-48e6-a392-d4e60377cbc2"
                },
                {
                    "data": {
                        "mesh_path": "../Assets/box.fbx/Cube",
                        "transform": {
                            "pos": [
                                0.0,
                                0.0,
                                0.0
                            ],
                            "rot": [
                                0.0,
                                0.0,
                                0.0,
                                1.0
                            ],
                            "scale": [
                                1.0,
                                1.0,
                                1.0
                            ]
                        }
                    },
                    "id": "748e720f-780c-418b-8751-d94448654ca1",
                    "name": "StaticMeshRenderer",
                    "parent": "2fcbd43a-f12e-48e6-a392-d4e60377cbc2"
                }
            ],
            "id": "971cb4b8-d224-4279-ba9a-fcb92dd7ca52"
        },
        {
            "components": [
                {
                    "data": {
                        "mass": 1.0,
                        "physics_simulation": true,
                        "transform": {
                            "pos": [
                                2.0,
                                44.0,
                                0.0
                            ],
                            "rot": [
                                0.3535533845424652,
                                0.3535533845424652,
                                -0.1464466005563736,
                                0.8535533547401428
                            ],
                            "scale": [
                                1.0,
                                1.0,
                                1.0
                            ]
                        },
                        "type": 1
                    },
                    "id": "eaa11478-de85-485c-8506-c483bc513f58",
                    "name": "RigidBodyCubeComponent"
                },
                {
                    "data": {
                        "mass": 1.0,
                        "physics_simulation": true,
                        "transform": {
                            "pos": [
                                0.0,
                                0.0,
                                0.0
                            ],
                            "rot": [
                                0.0,
                                0.0,
                                0.0,
                                1.0
                            ],
                            "scale": [
                                1.0,
                                1.0,
                                1.0
                            ]
                        },
                        "type": 1
                    },
                    "id": "fe29bb63-33d3-48b8-b8c4-c0f58fcc47a5",
                    "name": "RigidBodyCubeComponent",
                    "parent": "eaa11478-de85-485c-8506-c483bc513f58"
                },
                {
                    "data": {
                        "mesh_path": "../Assets/box.fbx/Cube",
                        "transform": {
                            "pos": [
                                0.0,
                                0.0,
                                0.0
                            ],
                            "rot": [
                                0.0,
                                0.0,
                                0.0,
                                1.0
                            ],
                            "scale": [
                                1.0,
                                1.0,
                                1.0
                            ]
                        }
                    },
                    "id": "e4a9f2ce-e614-4ed1-97d7-a5122a8b050e",
                    "name": "StaticMeshRenderer",
                    "parent": "eaa11478-de85-485c-8506-c483bc513f58"
                }
            ],
            "id": "4df2633b-dff6-4f25-9e9e-6eab89b58592"
        },
        {
            "components": [
                {
                    "data": {
                        "mass": 1.0,
                        "physics_simulation": true,
                        "transform": {
                            "pos": [
                                3.0,
                                40.0,
                                0.0
                            ],
                            "rot": [
                                0.3535533845424652,
                                0.3535533845424652,
                                -0.1464466005563736,
                                0.8535533547401428
                            ],
                            "scale": [
                                1.0,
                                1.0,
                                1.0
                            ]
                        },
                        "type": 1
                    },
                    "id": "5a3ee37b-353e-41bf-abe1-ac140e0afd81",
                    "name": "RigidBodyCubeComponent"
                },
                {
                    "data": {
                        "mass": 1.0,
                        "physics_simulation": true,
                        "transform": {
                            "pos": [
                                0.0,
                                0.0,
                                0.0
                            ],
                            "rot": [
                                0.0,
                                0.0,
                                0.0,
                                1.0
                            ],
                            "scale": [
                                1.0,
                                1.0,
                                1.0
                            ]
                        },
                        "type": 1
                    },
                    "id": "29266192-080f-4c5d-b823-2f5923c90582",
                    "name": "RigidBodyCubeComponent",
                    "parent": "5a3ee37b-353e-41bf-abe1-ac140e0afd81"
                },
                {
                    "data": {
                        "mesh_path": "../Assets/box.fbx/Cube",
                        "transform": {
                            "pos": [
                                0.0,
                                0.0,
                                0.0
                            ],
                            "rot": [
                                0.0,
                                0.0,
                                0.0,
                                1.0
                            ],
                            "scale": [
                                1.0,
                                1.0,
                                1.0
                            ]
                        }
                    },
                    "id": "25293821-bc23-401d-8b87-8c30b703e48b",
                    "name": "StaticMeshRenderer",
                    "parent": "5a3ee37b-353e-41bf-abe1-ac140e0afd81"
                }
            ],
            "id": "af9626af-be62-4b6a-8648-392eda2c5d03"
        },
        {
            "components": [
                {
                    "data": {
                        "mass": 1.0,
                        "physics_simulation": true,
                        "transform": {
                            "pos": [
                                3.0,
                                41.0,
                                0.0
                            ],
                            "rot": [
                                0.3535533845424652,
                                0.3535533845424652,
                                -0.1464466005563736,
                                0.8535533547401428
                            ],
                            "scale": [
                                1.0,
                                1.0,
                                1.0
                            ]
                        },
                        "type": 1
                    },
                    "id": "40b71f7a-843c-47df-85fa-2d36958e3352",
                    "name": "RigidBodyCubeComponent"
                },
                {
                    "data": {
                        "mass": 1.0,
                        "physics_simulation": true,
                        "transform": {
                            "pos": [
                                0.0,
                                0.0,
                                0.0
                            ],
                            "rot": [
                                0.0,
                                0.0,
                                0.0,
                                1.0
                            ],
                            "scale": [
                                1.0,
                                1.0,
                                1.0
                            ]
                        },
                        "type": 1
                    },
                    "id": "4006a24e-1e02-4b5f-ab27-93ebbf0f8dbd",
                    "name": "RigidBodyCubeComponent",
                    "parent": "40b71f7a-843c-47df-85fa-2d36958e3352"
                },
                {
                    "data": {
                        "mesh_path": "../Assets/box.fbx/Cube",
                        "transform": {
                            "pos": [
                                0.0,
                                0.0,
                                0.0
                            ],
                            "rot": [
                                0.0,
                                0.0,
                                0.0,
                                1.0
                            ],
                            "scale": [
                                1.0,
                                1.0,
                                1.0
                            ]
                        }
                    },
                    "id": "b4937356-c5d6-41ef-a01f-e374b40af135",
                    "name": "StaticMeshRenderer",
                    "parent": "40b71f7a-843c-47df-85fa-2d36958e3352"
                }
            ],
            "id": "e26ddf0a-7c56-4c9f-b6ba-99c2e9f42539"
        },
        {
            "components": [
                {
                    "data": {
                        "mass": 1.0,
                        "physics_simulation": true,
                        "transform": {
                            "pos": [
                                3.0,
                                42.0,
                                0.0
                            ],
                            "rot": [
                                0.3535533845424652,
                                0.3535533845424652,
                                -0.1464466005563736,
                                0.8535533547401428
                            ],
                            "scale": [
                                1.0,
                                1.0,
                                1.0
                            ]
                        },
                        "type": 1
                    },
                    "id": "5027888c-0334-4013-8f60-31ef542f8333",
                    "name": "RigidBodyCubeComponent"
                },
                {
                    "data": {
                        "mass": 1.0,
                        "physics_simulation": true,
                        "transform": {
                            "pos": [
                                0.0,
                                0.0,
                                0.0
                            ],
                            "rot": [
                                0.0,
                                0.0,
                                0.0,
                                1.0
                            ],
                            "scale": [
                                1.0,
                                1.0,
                                1.0
                            ]
                        },
                        "type": 1
                    },
                    "id": "8d523764-1138-4994-84b3-1cb09b1463e6",
                    "name": "RigidBodyCubeComponent",
                    "parent": "5027888c-0334-4013-8f60-31ef542f8333"
                },
                {
                    "data": {
                        "mesh_path": "../Assets/box.fbx/Cube",
                        "transform": {
                            "pos": [
                                0.0,
                                0.0,
                                0.0
                            ],
                            "rot": [
                                0.0,
                                0.0,
                                0.0,
                                1.0
                            ],
                            "scale": [
                                1.0,
                                1.0,
                                1.0
                            ]
                        }
                    },
                    "id": "472c811b-526c-409c-9922-36cb72d48e9a",
                    "name": "StaticMeshRenderer",
                    "parent": "5027888c-0334-4013-8f60-31ef542f8333"
                }
            ],
            "id": "6ee0540d-75ee-4dcb-8e39-8746ef1b2c19"
        },
        {
            "components": [
                {
                    "data": {
                        "mass": 1.0,
                        "physics_simulation": true,
                        "transform": {
                            "pos": [
                                3.0,
                                43.0,
                                0.0
                            ],
                            "rot": [
                                0.3535533845424652,
                                0.3535533845424652,
                                -0.1464466005563736,
                                0.8535533547401428
                            ],
                            "scale": [
                                1.0,
                                1.0,
                                1.0
                            ]
                        },
                        "type": 1
                    },
                    "id": "1163e14c-6d09-4556-95e3-756dc008835d",
                    "name": "RigidBodyCubeComponent"
                },
                {
                    "data": {
                        "mass": 1.0,
                        "physics_simulation": true,
                        "transform": {
                            "pos": [
                                0.0,
                                0.0,
                                0.0
                            ],
                            "rot": [
                                0.0,
                                0.0,
                                0.0,
                                1.0
                            ],
                            "scale": [
                                1.0,
                                1.0,
                                1.0
                            ]
                        },
                        "type": 1
                    },
                    "id": "709eb846-2283-4e17-82e9-22fdc8c62b95",
                    "name": "RigidBodyCubeComponent",
                    "parent": "1163e14c-6d09-4556-95e3-756dc008835d"
                },
                {
                    "data": {
                        "mesh_path": "../Assets/box.fbx/Cube",
                        "transform": {
                            "pos": [
                                0.0,
                                0.0,
                                0.0
                            ],
                            "rot": [
                                0.0,
                                0.0,
                                0.0,
                                1.0
                            ],
                            "scale": [
                                1.0,
                                1.0,
                                1.0
                            ]
                        }
                    },
                    "id": "2cdd0ab4-0769-4c4f-8e26-022706683888",
                    "name": "StaticMeshRenderer",
                    "parent": "1163e14c-6d09-4556-95e3-756dc008835d"
                }
            ],
            "id": "517e606a-1596-42b1-94e7-aed9373e850e"
        },
        {
            "components": [
                {
                    "data": {
                        "mass": 1.0,
                        "physics_simulation": true,
                        "transform": {
                            "pos": [
                                3.0,
                                44.0,
                                0.0
                            ],
                            "rot": [
                                0.3535533845424652,
                                0.3535533845424652,
                                -0.1464466005563736,
                                0.8535533547401428
                            ],
                            "scale": [
                                1.0,
                                1.0,
                                1.0
                            ]
                        },
                        "type": 1
                    },
                    "id": "09337278-0298-4ed7-8ac5-8c2c7935c429",
                    "name": "RigidBodyCubeComponent"
                },
                {
                    "data": {
                        "mass": 1.0,
                        "physics_simulation": true,
                        "transform": {
                            "pos": [
                                0.0,
                                0.0,
                                0.0
                            ],
                            "rot": [
                                0.0,
                                0.0,
                                0.0,
                                1.0
                            ],
                            "scale": [
                                1.0,
                                1.0,
                                1.0
                            ]
                        },
                        "type": 1
                    },
                    "id": "57ccdd26-2475-48c1-b699-889773c75f4b",
                    "name": "RigidBodyCubeComponent",
                    "parent": "09337278-0298-4ed7-8ac5-8c2c7935c429"
                },
                {
                    "data": {
                        "mesh_path": "../Assets/box.fbx/Cube",
                        "transform": {
                            "pos": [
                                0.0,
                                0.0,
                                0.0
                            ],
                            "rot": [
                                0.0,
                                0.0,
                                0.0,
                                1.0
                            ],
                            "scale": [
                                1.0,
                                1.0,
                                1.0
                            ]
                        }
                    },
                    "id": "119efca9-56cc-4fc9-ba77-90b63ab20994",
                    "name": "StaticMeshRenderer",
                    "parent": "09337278-0298-4ed7-8ac5-8c2c7935c429"
                }
            ],
            "id": "ba33bdbc-5c09-4b43-ad0b-0b00c684871a"
        },
        {
            "components": [
                {
                    "data": {
                        "mass": 1.0,
                        "physics_simulation": true,
                        "transform": {
                            "pos": [
                                4.0,
                                40.0,
                                0.0
                            ],
                            "rot": [
                                0.3535533845424652,
                                0.3535533845424652,
                                -0.1464466005563736,
                                0.8535533547401428
                            ],
                            "scale": [
                                1.0,
                                1.0,
                                1.0
                            ]
                        },
                        "type": 1
                    },
                    "id": "5ae1fd44-6ebd-41a5-b451-d30bcaf29c1d",
                    "name": "RigidBodyCubeComponent"
                },
                {
                    "data": {
                        "mass": 1.0,
                        "physics_simulation": true,
                        "transform": {
                            "pos": [
                                0.0,
                                0.0,
                                0.0
                            ],
                            "rot": [
                                0.0,
                                0.0,
                                0.0,
                                1.0
                            ],
                            "scale": [
                                1.0,
                                1.0,
                                1.0
                            ]
                        },
                        "type": 1
                    },
                    "id": "0b9d581f-c2af-4787-b866-301a2ea1a935",
                    "name": "RigidBodyCubeComponent",
                    "parent": "5ae1fd44-6ebd-41a5-b451-d30bcaf29c1d"
                },
                {
                    "data": {
                        "mesh_path": "../Assets/box.fbx/Cube",
                        "transform": {
                            "pos": [
                                0.0,
                                0.0,
                                0.0
                            ],
                            "rot": [
                                0.0,
                                0.0,
                                0.0,
                                1.0
                            ],
                            "scale": [
                                1.0,
                                1.0,
                                1.0
                            ]
                        }
                    },
                    "id": "71123fdd-a202-4d6e-b6ca-66e68dbbcea2",
                    "name": "StaticMeshRenderer",
                    "parent": "5ae1fd44-6ebd-41a5-b451-d30bcaf29c1d"
                }
            ],
            "id": "88859e04-22f9-4410-8100-c30c5b2e3e1d"
        },
        {
            "components": [
                {
                    "data": {
                        "mass": 1.0,
                        "physics_simulation": true,
                        "transform": {
                            "pos": [
                                4.0,
                                41.0,
                                0.0
                            ],
                            "rot": [
                                0.3535533845424652,
                                0.3535533845424652,
                                -0.1464466005563736,
                                0.8535533547401428
                            ],
                            "scale": [
                                1.0,
                                1.0,
                                1.0
                            ]
                        },
                        "type": 1
                    },
                    "id": "6e2338ca-958c-4d63-8f71-351dbb478988",
                    "name": "RigidBodyCubeComponent"
                },
                {
                    "data": {
                        "mass": 1.0,
                        "physics_simulation": true,
                        "transform": {
                            "pos": [
                                0.0,
                                0.0,
                                0.0
                            ],
                            "rot": [
                                0.0,
                                0.0,
                                0.0,
                                1.0
                            ],
                            "scale": [
                                1.0,
                                1.0,
                                1.0
                            ]
                        },
                        "type": 1
                    },
                    "id": "aac91f22-0af2-4540-8d67-4c6a29e46c4e",
                    "name": "RigidBodyCubeComponent",
                    "parent": "6e2338ca-958c-4d63-8f71-351dbb478988"
                },
                {
                    "data": {
                        "mesh_path": "../Assets/box.fbx/Cube",
                        "transform": {
                            "pos": [
                                0.0,
                                0.0,
                                0.0
                            ],
                            "rot": [
                                0.0,
                                0.0,
                                0.0,
                                1.0
                            ],
                            "scale": [
                                1.0,
                                1.0,
                                1.0
                            ]
                        }
                    },
                    "id": "aa180e4c-fa53-4ede-ad8e-8efa19aa371d",
                    "name": "StaticMeshRenderer",
                    "parent": "6e2338ca-958c-4d63-8f71-351dbb478988"
                }
            ],
            "id": "ff013ad1-99db-4118-ab4d-3ddac8fb2880"
        },
        {
            "components": [
                {
                    "data": {
                        "mass": 1.0,
                        "physics_simulation": true,
                        "transform": {
                            "pos": [
                                4.0,
                                42.0,
                                0.0
                            ],
                            "rot": [
                                0.3535533845424652,
                                0.3535533845424652,
                                -0.1464466005563736,
                                0.8535533547401428
                            ],
                            "scale": [
                                1.0,
                                1.0,
                                1.0
                            ]
                        },
                        "type": 1
                    },
                    "id": "cd8b4944-646f-4cbf-a22f-e96daff127a6",
                    "name": "RigidBodyCubeComponent"
                },
                {
                    "data": {
                        "mass": 1.0,
                        "physics_simulation": true,
                        "transform": {
                            "pos": [
                                0.0,
                                0.0,
                                0.0
                            ],
                            "rot": [
                                0.0,
                                0.0,
                                0.0,
                                1.0
                            ],
                            "scale": [
                                1.0,
                                1.0,
                                1.0
                            ]
                        },
                        "type": 1
                    },
                    "id": "9cfa9ac0-813c-4775-8632-4d23a4b01ffc",
                    "name": "RigidBodyCubeComponent",
                    "parent": "cd8b4944-646f-4cbf-a22f-e96daff127a6"
                },
                {
                    "data": {
                        "mesh_path": "../Assets/box.fbx/Cube",
                        "transform": {
                            "pos": [
                                0.0,
                                0.0,
                                0.0
                            ],
                            "rot": [
                                0.0,
                                0.0,
                                0.0,
                                1.0
                            ],
                            "scale": [
                                1.0,
                                1.0,
                                1.0
                            ]
                        }
                    },
                    "id": "44cec5cf-00f3-44bd-8ade-e62eed74dbe1",
                    "name": "StaticMeshRenderer",
                    "parent": "cd8b4944-646f-4cbf-a22f-e96daff127a6"
                }
            ],
            "id": "45dc7bb8-35ba-42a7-95dd-cc9437861a9d"
        },
        {
            "components": [
                {
                    "data": {
                        "mass": 1.0,
                        "physics_simulation": true,
                        "transform": {
                            "pos": [
                                4.0,
                                43.0,
                                0.0
                            ],
                            "rot": [
                                0.3535533845424652,
                                0.3535533845424652,
                                -0.1464466005563736,
                                0.8535533547401428
                            ],
                            "scale": [
                                1.0,
                                1.0,
                                1.0
                            ]
                        },
                        "type": 1
                    },
                    "id": "2b91b4d8-4e3f-4aec-a2d8-113bf0e8635f",
                    "name": "RigidBodyCubeComponent"
                },
                {
                    "data": {
                        "mass": 1.0,
                        "physics_simulation": true,
                        "transform": {
                            "pos": [
                                0.0,
                                0.0,
                                0.0
                            ],
                            "rot": [
                                0.0,
                                0.0,
                                0.0,
                                1.0
                            ],
                            "scale": [
                                1.0,
                                1.0,
                                1.0
                            ]
                        },
                        "type": 1
                    },
                    "id": "9e638b23-061b-4273-a98f-97a77d24d0ba",
                    "name": "RigidBodyCubeComponent",
                    "parent": "2b91b4d8-4e3f-4aec-a2d8-113bf0e8635f"
                },
                {
                    "data": {
                        "mesh_path": "../Assets/box.fbx/Cube",
                        "transform": {
                            "pos": [
                                0.0,
                                0.0,
                                0.0
                            ],
                            "rot": [
                                0.0,
                                0.0,
                                0.0,
                                1.0
                            ],
                            "scale": [
                                1.0,
                                1.0,
                                1.0
                            ]
                        }
                    },
                    "id": "298fea1d-7f90-4853-b5c0-8af34791b330",
                    "name": "StaticMeshRenderer",
                    "parent": "2b91b4d8-4e3f-4aec-a2d8-113bf0e8635f"
                }
            ],
            "id": "40804299-1957-4aa6-ab6e-83e44d50a8af"
        },
        {
            "components": [
                {
                    "data": {
                        "mass": 1.0,
                        "physics_simulation": true,
                        "transform": {
                            "pos": [
                                4.0,
                                44.0,
                                0.0
                            ],
                            "rot": [
                                0.3535533845424652,
                                0.3535533845424652,
                                -0.1464466005563736,
                                0.8535533547401428
                            ],
                            "scale": [
                                1.0,
                                1.0,
                                1.0
                            ]
                        },
                        "type": 1
                    },
                    "id": "456bd824-9f8f-4fe3-ad0d-6d0f984b6120",
                    "name": "RigidBodyCubeComponent"
                },
                {
                    "data": {
                        "mass": 1.0,
                        "physics_simulation": true,
                        "transform": {
                            "pos": [
                                0.0,
                                0.0,
                                0.0
                            ],
                            "rot": [
                                0.0,
                                0.0,
                                0.0,
                                1.0
                            ],
                            "scale": [
                                1.0,
                                1.0,
                                1.0
                            ]
                        },
                        "type": 1
                    },
                    "id": "5328b0f1-db3b-4b7f-a688-cae865313d09",
                    "name": "RigidBodyCubeComponent",
                    "parent": "456bd824-9f8f-4fe3-ad0d-6d0f984b6120"
                },
                {
                    "data": {
                        "mesh_path": "../Assets/box.fbx/Cube",
                        "transform": {
                            "pos": [
                                0.0,
                                0.0,
                                0.0
                            ],
                            "rot": [
                                0.0,
                                0.0,
                                0.0,
                                1.0
                            ],
                            "scale": [
                                1.0,
                                1.0,
                                1.0
                            ]
                        }
                    },
                    "id": "ee8c3505-c955-4d18-af5e-836bcbc1993d",
                    "name": "StaticMeshRenderer",
                    "parent": "456bd824-9f8f-4fe3-ad0d-6d0f984b6120"
                }
            ],
            "id": "5a9ffa5a-07ec-4d29-8f6d-2a909e87d2d2"
        },
        {
            "components": [
                {
                    "data": {
                        "mesh_path": "../Assets/box.fbx/Cube",
                        "transform": {
                            "pos": [
                                16.0,
                                3.0,
                                0.0
                            ],
                            "rot": [
                                0.0,
                                0.0,
                                0.0,
                                1.0
                            ],
                            "scale": [
                                4.0,
                                4.0,
                                20.0
                            ]
                        }
                    },
                    "id": "83fb1959-8a49-49aa-a193-2675019f56bb",
                    "name": "StaticMeshRenderer"
                }
            ],
            "id": "dae6ec86-065c-4e8f-ad70-97dcb9350f16"
        },
        {
            "components": [
                {
                    "data": {
                        "transform": {
                            "pos": [
                                11.637999534606934,
                                3.4630000591278076,
                                -7.673999786376953
                            ],
                            "rot": [
                                0.0,
                                0.0,
                                0.0,
                                1.0
                            ],
                            "scale": [
                                1.0,
                                1.0,
                                1.0
                            ]
                        }
                    },
                    "id": "d576d230-4271-44dc-bab3-ac65a91c1fa7",
                    "name": "SceneComponent"
                }
            ],
            "id": "c7574044-eaae-4a89-957f-f956478ca4d4"
        },
        {
            "components": [
                {
                    "data": {
                        "mesh_path": "../Assets/tjciddjqx_LOD0.fbx/Aset_edible_baked_goods_S_tjciddjqx_LOD0",
                        "transform": {
                            "pos": [
                                11.435999870300293,
                                0.8429999947547913,
                                -2.502000093460083
                            ],
                            "rot": [
                                0.0,
                                0.0,
                                0.0,
                                1.0
                            ],
                            "scale": [
                                0.4000000059604645,
                                0.4000000059604645,
                                0.4000000059604645
                            ]
                        }
                    },
                    "id": "9bdfecec-e846-46a7-8ec5-f6673c36dfd3",
                    "name": "StaticMeshRenderer"
                }
            ],
            "id": "5001c165-8ec8-4657-933f-6802e05244fe"
        },
        {
            "components": [
                {
                    "data": {
                        "transform": {
                            "pos": [
                                0.0,
                                3.0,
                                0.0
                            ],
                            "rot": [
                                0.0,
                                0.0,
                                0.0,
                                1.0
                            ],
                            "scale": [
                                1.5,
                                3.0,
                                1.5
                            ]
                        }
                    },
                    "id": "eb61ef53-fdf5-414e-bc2c-19fb489ffb7f",
                    "name": "MovementComponent"
                },
                {
                    "data": {
                        "mesh_path": "../Assets/box.fbx/Cube",
                        "transform": {
                            "pos": [
                                0.0,
                                0.0,
                                0.0
                            ],
                            "rot": [
                                0.0,
                                0.0,
                                0.0,
                                1.0
                            ],
                            "scale": [
                                1.0,
                                1.0,
                                1.0
                            ]
                        }
                    },
                    "id": "3d8bae92-5267-4ab6-8c60-3460b7a0573d",
                    "name": "StaticMeshRenderer",
                    "parent": "eb61ef53-fdf5-414e-bc2c-19fb489ffb7f"
                }
            ],
            "id": "c6723bab-26ca-4e51-9b47-2fa4c325480e"
        },
        {
            "components": [
                {
                    "data": {
                        "transform": {
                            "pos": [
                                6.564332485198975,
                                0.0,
                                -5.811928749084473
                            ],
                            "rot": [
                                -0.0,
                                0.0,
                                -0.0,
                                1.0
                            ],
                            "scale": [
                                0.4000000059604645,
                                0.4000000059604645,
                                0.4000000059604645
                            ]
                        }
                    },
                    "id": "55448b77-62ad-4f4d-b670-76823ac5fe24",
                    "name": "SceneComponent"
                },
                {
                    "data": {
                        "mesh_path": "../Assets/tjciddjqx_LOD0.fbx/Aset_edible_baked_goods_S_tjciddjqx_LOD0",
                        "transform": {
                            "pos": [
                                0.0,
                                0.0,
                                0.0
                            ],
                            "rot": [
                                0.0,
                                0.0,
                                0.0,
                                1.0
                            ],
                            "scale": [
                                1.0,
                                1.0,
                                1.0
                            ]
                        }
                    },
                    "id": "ab9ee69c-89ef-4d28-ae2e-80a801a845e2",
                    "name": "StaticMeshRenderer",
                    "parent": "55448b77-62ad-4f4d-b670-76823ac5fe24"
                },
                {
                    "data": {
                        "transform": {
                            "pos": [
                                0.0,
                                0.0,
                                0.0
                            ],
                            "rot": [
                                0.0,
                                0.0,
                                0.0,
                                1.0
                            ],
                            "scale": [
                                1.0,
                                1.0,
                                1.0
                            ]
                        }
                    },
                    "id": "5277403f-06ea-4640-8999-01f42024ff4d",
                    "name": "SceneComponent",
                    "parent": "55448b77-62ad-4f4d-b670-76823ac5fe24"
                },
                {
                    "data": {
                        "mesh_path": "../Assets/stanford-bunny.fbx/Stanford Bunny-mesh",
                        "transform": {
                            "pos": [
                                0.0,
                                3.4630000591278076,
                                0.0
                            ],
                            "rot": [
                                0.0,
                                0.0,
                                0.0,
                                1.0
                            ],
                            "scale": [
                                0.014999999664723873,
                                0.014999999664723873,
                                0.014999999664723873
                            ]
                        }
                    },
                    "id": "b8ee1bb3-57b3-4c72-8e17-cbddd4d65613",
                    "name": "StaticMeshRenderer",
                    "parent": "5277403f-06ea-4640-8999-01f42024ff4d"
                }
            ],
            "id": "799451f7-3b54-4b2f-94ec-403c66cf9b45"
        }
    ]
}
